{
  "indexes": [
    {
      "collectionGroup": "checkins",
      "queryScope": "COLLECTION",
      "fields": [
        { "fieldPath": "userId", "order": "ASCENDING" },
        { "fieldPath": "createdAt", "order": "DESCENDING" }
      ]
    },
    {
      "collectionGroup": "plans",
      "queryScope": "COLLECTION",
      "fields": [
        { "fieldPath": "active", "order": "ASCENDING" },
        { "fieldPath": "classesPerWeek", "order": "ASCENDING" }
      ]
    }
  ],
  "fieldOverrides": []
}
